{"count":"1","infocode":"10000","pois":[{"parent":"B0MUF7HVMV","address":"广州路与上海路交叉口西160米","business":{"keytag":"风景名胜,风景名胜,观景点","rating":"3.8","business_area":"南大"},"distance":"","pcode":"320000","adcode":"320106","pname":"江苏省","cityname":"南京市","type":"风景名胜;风景名胜;观景点","photos":[{"title":"","url":"http://store.is.autonavi.com/showpic/53b1090ea3a835fbcfe3e2c5929c977c"},{"title":"","url":"http://store.is.autonavi.com/showpic/9a0807445a3a22c7abcc4f3d3a201033"},{"title":"","url":"https://store.is.autonavi.com/showpic/0d3242620989688d0000003039554458?type=pic"}],"typecode":"110209","adname":"鼓楼区","citycode":"025","name":"先锋书店(五台山总店)-大地上的异乡者文字墙(打卡点)","location":"118.774188,32.050440","id":"B0MUF7HHE8"}],"status":"1","info":"OK"}