{"profile":{"city":"南京市","days":4,"preferences":["自然风光","人文古迹","亲子"],"pace":"适中","transport":"公共交通","budget":15000},"plans":[{"title":"经济","description":"以预算下限为优先，保留必要体验与交通","personalizedAdvice":"带小孩建议D1玄武湖多休息，D2牛首山备足饮水，D3雨花台室内为主。","score":96,"days":[{"day":1,"date":"2026-07-16","theme":"玄武区","dailyAdvice":"D1天气炎热，玄武湖可乘船或树荫下休憩；紫金山天文台拥挤，建议缩短停留。","weather":{"provider":"WeatherAPI","condition":"Sunny","minTemp":27.4,"maxTemp":34.4,"rainProbability":11,"wind":"21.6 km/h","advice":"天气总体适宜，仍请出发前复核临近预报","forecastTime":"2026-07-16"},"totalMinutes":727,"travelKm":7.9,"accommodation":{"name":"璞林酒店(南京林业大学玄武湖店)","address":"玄武科技金融园c1栋璞林酒店","rating":4.7,"longitude":118.820624,"latitude":32.066653,"sameAsPrevious":false,"policy":"13:00后入住 · 次日13:00前退房","luggagePlan":"上午先到酒店寄存行李，游览结束且13:00后办理入住"},"scheduleNotes":["07:00—07:30 起床与洗漱","07:30—07:50 到达璞林酒店(南京林业大学玄武湖店)，前台寄存行李（13:00后办理入住）","07:50—07:54 步行从住宿前往早餐门店，约4分钟（高德步行路线）","07:54—08:34 早餐推荐：侯志伟土豆泥拌粉（高德评分4.1），板仓街11号","08:34—08:47 步行前往玄武湖公园，约13分钟（高德步行路线）","天气：Sunny，27.4—34.4℃，降雨概率11%。天气总体适宜，仍请出发前复核临近预报","11:47—12:26 公交 G33路：龙蟠路·岗子村→紫金山索道；315路：龙蟠路·岗子村→紫金山索道前往紫金山天文台，约39分钟（高德公共交通路线）","12:26—13:05 公交 6路：板仓街·岗子村→板仓村；313路：板仓街·岗子村→板仓村；131路：板仓街·岗子村→板仓村前往午餐门店，约39分钟（高德公共交通路线）","13:05—14:05 午餐推荐：侯志伟土豆泥拌粉（高德评分4.1），板仓街11号","14:05—14:53 公交 315路：龙蟠路·岗子村→紫金山索道；G33路：龙蟠路·岗子村→紫金山索道返回紫金山天文台，约48分钟（高德公共交通路线）","16:53—17:37 公交 20路：紫金山索道→太平门；11路：太平门→板仓街·岗子村；70路：太平门→板仓街·岗子村前往璞林酒店(南京林业大学玄武湖店)办理入住，约44分钟（高德公共交通路线）","17:37—17:57 办理入住并将寄存行李送入客房","17:57—18:02 步行前往晚餐门店，约5分钟（高德步行路线）","18:02—19:02 晚餐推荐：云南过桥米线(南京玄武区)（高德评分4.5），板仓街8-2号(岗子村地铁站1号口步行400米)","19:02—19:07 步行返回住宿璞林酒店(南京林业大学玄武湖店)，约5分钟（高德步行路线）"],"stops":[{"attractionId":15,"name":"玄武湖公园","category":"自然风光、城市公园","time":"08:47","endTime":"11:47","transferToNextMinutes":39,"durationMinutes":180,"heatScore":98,"crowdIndex":54,"crowdLevel":"舒适","openingHours":"24小时营业","crowdAdvice":"预计客流可接受，仍请出发前查看景区官方提示","bestVisitTime":"08:00","crowdBasis":"预测模型：景点热度、周边POI距离衰减、日期时段和天气","summary":"南京旅游 RAG 数据集收录。出发前请复核开放、预约和票价信息。","personalTip":"带小孩可租船游湖或去儿童乐园，注意防暑。","longitude":118.812688,"latitude":32.069455,"freshness":"今日更新","traffic":{"liveLevel":"未知","roadName":"","description":"未找到可查询的景区周边道路，暂不支持实时路况","sampledAt":"2026-07-16 16:35","averageSpeed":null,"forecastLevel":"未知","forecastReason":"依据近60天同星期及时段的非通勤、非节假日、非异常路况样本","noiseNote":"未发现已识别的通勤或异常噪声","available":true}},{"attractionId":23,"name":"紫金山天文台","category":"博物馆、自然科学、历史人文","time":"14:53","endTime":"16:53","transferToNextMinutes":0,"durationMinutes":120,"heatScore":88,"crowdIndex":84,"crowdLevel":"拥挤","openingHours":"以景区公告为准","crowdAdvice":"当前时段预计拥挤，建议改到8:00左右或选择备选景点","bestVisitTime":"08:00","crowdBasis":"预测模型：景点热度、周边POI距离衰减、日期时段和天气","summary":"南京旅游 RAG 数据集收录。出发前请复核开放、预约和票价信息。","personalTip":"天文台科普性强，但拥挤，建议重点参观天文望远镜展区。","longitude":118.829655,"latitude":32.064948,"freshness":"今日更新","traffic":{"liveLevel":"未知","roadName":"","description":"未找到可查询的景区周边道路，暂不支持实时路况","sampledAt":"2026-07-16 16:35","averageSpeed":null,"forecastLevel":"未知","forecastReason":"依据近60天同星期及时段的非通勤、非节假日、非异常路况样本","noiseNote":"未发现已识别的通勤或异常噪声","available":true}}],"costs":[{"category":"住宿","label":"当晚住宿","amount":220,"source":"预算估算：高德住宿 POI 与档位基准","pending":false},{"category":"餐饮","label":"早餐","amount":18,"source":"预算估算：高德周边餐饮","pending":false},{"category":"餐饮","label":"午餐","amount":42,"source":"预算估算：高德周边餐饮","pending":false},{"category":"餐饮","label":"晚餐","amount":58,"source":"预算估算：高德周边餐饮","pending":false},{"category":"门票","label":"玄武湖公园 门票","amount":0,"source":"高德 POI 类别，按免费开放估算","pending":false},{"category":"门票","label":"紫金山天文台 门票","amount":96,"source":"预算估算：高德 POI 未提供实时票价","pending":false},{"category":"交通","label":"当日高德路线交通","amount":4,"source":"预算估算：高德路线距离与交通方式","pending":false},{"category":"预留","label":"弹性消费与价格浮动预留","amount":2187,"source":"预算预留","pending":false}]},{"day":2,"date":"2026-07-17","theme":"江宁区","dailyAdvice":"D2降雨概率高，牛首山室内佛殿为主，带雨具，注意防滑。","weather":{"provider":"WeatherAPI","condition":"Sunny","minTemp":27.2,"maxTemp":33.8,"rainProbability":70,"wind":"23.0 km/h","advice":"降雨概率较高，建议准备雨具并优先室内行程","forecastTime":"2026-07-17"},"totalMinutes":764,"travelKm":32.9,"accommodation":{"name":"南京牛首山希尔顿酒店","address":"宁丹大道8号","rating":4.7,"longitude":118.753887,"latitude":31.912211,"sameAsPrevious":false,"policy":"13:00后入住 · 次日13:00前退房","luggagePlan":"13:00前从上一酒店退房，仅在酒店转场时携带行李；到新酒店后立即寄存，13:00后入住"},"scheduleNotes":["07:00—07:30 起床与洗漱","07:30—07:34 步行从住宿前往早餐门店，约4分钟（高德步行路线）","07:34—08:14 早餐推荐：侯志伟土豆泥拌粉（高德评分4.1），板仓街11号","08:14—08:18 步行返回原住宿办理退房，约4分钟（高德步行路线）","08:18—08:33 在璞林酒店(南京林业大学玄武湖店)办理退房（酒店要求13:00前）","08:33—10:01 地铁 地铁4号线：岗子村→鼓楼；地铁1号线：鼓楼→天隆寺；712路：天隆寺地铁站→牛首山风景区携带行李前往新住宿南京牛首山希尔顿酒店，约88分钟（高德公共交通路线）","10:01—10:16 在新住宿前台寄存行李，13:00后办理入住","10:16—10:22 打车从新住宿前往牛首山文化旅游区，约6分钟（高德驾车路线）","天气：Sunny，27.2—33.8℃，降雨概率70%。降雨概率较高，建议准备雨具并优先室内行程","10:22—11:30 景点周边短暂休息","11:30—11:50 步行前往午餐门店，约20分钟（高德步行路线）","11:50—12:50 午餐推荐：半山面馆(牛首山店)（高德评分4.1），宁丹大道18号南京牛首山文化旅游区","12:50—13:10 步行返回牛首山文化旅游区，约20分钟（高德步行路线）","18:10—18:16 打车前往南京牛首山希尔顿酒店办理入住，约6分钟（高德驾车路线）","18:16—18:36 办理入住并将寄存行李送入客房","18:36—18:40 步行前往晚餐门店，约4分钟（高德步行路线）","18:40—19:40 晚餐推荐：复兴园中式糕团（高德评分4.2），牛首山东门出入口大巴车停车东北角售票大厅楼下","19:40—19:44 步行返回住宿南京牛首山希尔顿酒店，约4分钟（高德步行路线）"],"stops":[{"attractionId":19,"name":"牛首山文化旅游区","category":"历史人文、自然风光、风景名胜","time":"13:10","endTime":"18:10","transferToNextMinutes":0,"durationMinutes":300,"heatScore":98,"crowdIndex":35,"crowdLevel":"舒适","openingHours":"以景区公告为准","crowdAdvice":"预计客流可接受，仍请出发前查看景区官方提示","bestVisitTime":"08:00","crowdBasis":"预测模型：景点热度、周边POI距离衰减、日期时段和天气","summary":"南京旅游 RAG 数据集收录。出发前请复核开放、预约和票价信息。","personalTip":"佛顶宫和地宫适合亲子，提前预约，带足零食和水。","longitude":118.74415,"latitude":31.903309,"freshness":"今日更新","traffic":{"liveLevel":"未知","roadName":"","description":"未找到可查询的景区周边道路，暂不支持实时路况","sampledAt":"2026-07-16 16:35","averageSpeed":null,"forecastLevel":"未知","forecastReason":"依据近60天同星期及时段的非通勤、非节假日、非异常路况样本","noiseNote":"未发现已识别的通勤或异常噪声","available":true}}],"costs":[{"category":"住宿","label":"当晚住宿","amount":220,"source":"预算估算：高德住宿 POI 与档位基准","pending":false},{"category":"餐饮","label":"早餐","amount":18,"source":"预算估算：高德周边餐饮","pending":false},{"category":"餐饮","label":"午餐","amount":42,"source":"预算估算：高德周边餐饮","pending":false},{"category":"餐饮","label":"晚餐","amount":58,"source":"预算估算：高德周边餐饮","pending":false},{"category":"门票","label":"牛首山文化旅游区 门票","amount":96,"source":"预算估算：高德 POI 未提供实时票价","pending":false},{"category":"交通","label":"当日高德路线交通","amount":15,"source":"预算估算：高德路线距离与交通方式","pending":false},{"category":"预留","label":"弹性消费与价格浮动预留","amount":2176,"source":"预算预留","pending":false}]},{"day":3,"date":"2026-07-18","theme":"雨花台区 · 秦淮区","dailyAdvice":"D3降雨概率高，雨花台烈士陵园室内纪念馆为主，秦淮河画舫备雨衣。","weather":{"provider":"WeatherAPI","condition":"Partly Cloudy","minTemp":24.5,"maxTemp":27.3,"rainProbability":85,"wind":"16.6 km/h","advice":"降雨概率较高，建议准备雨具并优先室内行程","forecastTime":"2026-07-18"},"totalMinutes":737,"travelKm":24.9,"accommodation":{"name":"南京花迹民宿(夫子庙老门东店)","address":"老门东中营52号(瓦库餐厅对面)","rating":4.8,"longitude":118.78813,"latitude":32.011212,"sameAsPrevious":false,"policy":"13:00后入住 · 次日13:00前退房","luggagePlan":"13:00前从上一酒店退房，仅在酒店转场时携带行李；到新酒店后立即寄存，13:00后入住"},"scheduleNotes":["07:00—07:30 起床与洗漱","07:30—07:40 步行从住宿前往早餐门店，约10分钟（高德步行路线）","07:40—08:20 早餐推荐：鸭得堡老鸭汤鸭血粉丝(牛首山东门店)（高德评分4.1），宁丹大道18号南京牛首山文化旅游区内(东侧)","08:20—08:30 步行返回原住宿办理退房，约10分钟（高德步行路线）","08:30—08:45 在南京牛首山希尔顿酒店办理退房（酒店要求13:00前）","08:45—10:03 地铁 G70路：牛首山景区→天元西路地铁站；地铁3号线：天元西路→武定门携带行李前往新住宿南京花迹民宿(夫子庙老门东店)，约78分钟（高德公共交通路线）","10:03—10:18 在新住宿前台寄存行李，13:00后办理入住","10:18—11:00 地铁 地铁3号线：武定门→卡子门；地铁10号线：卡子门→雨花台从新住宿前往雨花台风景区，约42分钟（高德公共交通路线）","天气：Partly Cloudy，24.5—27.3℃，降雨概率85%。降雨概率较高，建议准备雨具并优先室内行程","11:00—11:30 景点周边短暂休息","11:30—11:45 步行前往午餐门店，约15分钟（高德步行路线）","11:45—12:45 午餐推荐：汪家馄饨(汇芯谷店)（高德评分4.7），雨花路201号云乐购物中心一楼门面房","12:45—13:00 步行返回雨花台风景区，约15分钟（高德步行路线）","16:00—16:39 地铁 地铁10号线：雨花台→卡子门；地铁3号线：卡子门→夫子庙前往秦淮河画舫夜游，约39分钟（高德公共交通路线）","17:39—17:56 步行前往南京花迹民宿(夫子庙老门东店)办理入住，约17分钟（高德步行路线）","17:56—18:16 办理入住并将寄存行李送入客房","18:16—18:17 步行前往晚餐门店，约1分钟（高德步行路线）","18:17—19:17 晚餐推荐：老虎堂黑糖專壳(老门东店)（高德评分4.4），老门东箍桶巷130号"],"stops":[{"attractionId":29,"name":"雨花台风景区","category":"历史人文、城市公园","time":"13:00","endTime":"16:00","transferToNextMinutes":39,"durationMinutes":180,"heatScore":97,"crowdIndex":55,"crowdLevel":"舒适","openingHours":"08:30-17:00","crowdAdvice":"预计客流可接受，仍请出发前查看景区官方提示","bestVisitTime":"08:00","crowdBasis":"预测模型：景点热度、周边POI距离衰减、日期时段和天气","summary":"南京旅游 RAG 数据集收录。出发前请复核开放、预约和票价信息。","personalTip":"带孩子了解历史，纪念馆内凉爽，注意保持安静。","longitude":118.781727,"latitude":31.997896,"freshness":"今日更新","traffic":{"liveLevel":"未知","roadName":"","description":"未找到可查询的景区周边道路，暂不支持实时路况","sampledAt":"2026-07-16 16:35","averageSpeed":null,"forecastLevel":"未知","forecastReason":"依据近60天同星期及时段的非通勤、非节假日、非异常路况样本","noiseNote":"未发现已识别的通勤或异常噪声","available":true}},{"attractionId":33,"name":"秦淮河画舫夜游","category":"夜游、体验项目","time":"16:39","endTime":"17:39","transferToNextMinutes":0,"durationMinutes":60,"heatScore":98,"crowdIndex":76,"crowdLevel":"较拥挤","openingHours":"24小时营业","crowdAdvice":"客流偏高，建议提前预约并尽量在8:00左右到达","bestVisitTime":"08:00","crowdBasis":"预测模型：景点热度、周边POI距离衰减、日期时段和天气","summary":"南京旅游 RAG 数据集收录。出发前请复核开放、预约和票价信息。","personalTip":"夜游画舫浪漫，但人多，建议提前购票，抱好小孩。","longitude":118.792026,"latitude":32.021196,"freshness":"今日更新","traffic":{"liveLevel":"未知","roadName":"","description":"未找到可查询的景区周边道路，暂不支持实时路况","sampledAt":"2026-07-16 16:35","averageSpeed":null,"forecastLevel":"未知","forecastReason":"依据近60天同星期及时段的非通勤、非节假日、非异常路况样本","noiseNote":"未发现已识别的通勤或异常噪声","available":true}}],"costs":[{"category":"住宿","label":"当晚住宿","amount":220,"source":"预算估算：高德住宿 POI 与档位基准","pending":false},{"category":"餐饮","label":"早餐","amount":18,"source":"预算估算：高德周边餐饮","pending":false},{"category":"餐饮","label":"午餐","amount":42,"source":"预算估算：高德周边餐饮","pending":false},{"category":"餐饮","label":"晚餐","amount":58,"source":"预算估算：高德周边餐饮","pending":false},{"category":"门票","label":"雨花台风景区 门票","amount":0,"source":"高德 POI 类别，按免费开放估算","pending":false},{"category":"门票","label":"秦淮河画舫夜游 门票","amount":40,"source":"预算估算：高德 POI 未提供实时票价","pending":false},{"category":"交通","label":"当日高德路线交通","amount":12,"source":"预算估算：高德路线距离与交通方式","pending":false},{"category":"预留","label":"弹性消费与价格浮动预留","amount":2235,"source":"预算预留","pending":false}]},{"day":4,"date":"2026-07-19","theme":"栖霞区 · 鼓楼区","dailyAdvice":"D4幕燕滨江和阅江楼步行较多，注意孩子体力，适当休息。","weather":null,"totalMinutes":820,"travelKm":36.7,"accommodation":{"name":"悦见公寓(五塘广场地铁站店)","address":"幕府山街道幕府西路29号金域中央广场","rating":5.0,"longitude":118.773075,"latitude":32.106575,"sameAsPrevious":false,"policy":"13:00后入住 · 次日13:00前退房","luggagePlan":"13:00前从上一酒店退房，仅在酒店转场时携带行李；到新酒店后立即寄存，13:00后入住"},"scheduleNotes":["07:00—07:30 起床与洗漱","07:30—07:31 步行从住宿前往早餐门店，约1分钟（高德步行路线）","07:31—08:11 早餐推荐：茶颜悦色(南京老门东游园会店)（高德评分4.6），剪子巷54号老门东星巴克对面","08:11—08:12 步行返回原住宿办理退房，约1分钟（高德步行路线）","08:12—08:27 在南京花迹民宿(夫子庙老门东店)办理退房（酒店要求13:00前）","08:27—09:17 地铁 地铁3号线：武定门→五塘广场携带行李前往新住宿悦见公寓(五塘广场地铁站店)，约50分钟（高德公共交通路线）","09:17—09:32 在新住宿前台寄存行李，13:00后办理入住","09:32—09:48 打车从新住宿前往幕燕滨江风貌区，约16分钟（高德驾车路线）","09:48—11:30 景点周边短暂休息","11:30—11:42 打车前往午餐门店，约12分钟（高德驾车路线）","11:42—12:42 午餐推荐：和善园(南京幕府东路店)（高德评分3.8），幕府东路云谷山庄菜场","12:42—12:54 打车返回幕燕滨江风貌区，约12分钟（高德驾车路线）","15:54—17:09 地铁 地铁7号线：幕府山→福建路；地铁5号线：福建路→盐仓桥前往阅江楼，约75分钟（高德公共交通路线）","19:09—19:19 打车前往悦见公寓(五塘广场地铁站店)办理入住，约10分钟（高德驾车路线）","19:19—19:39 办理入住并将寄存行李送入客房","19:39—19:40 步行前往晚餐门店，约1分钟（高德步行路线）","19:40—20:40 晚餐推荐：小马牛肉面(星河广场店)（高德评分4.2），幕府西路13-6号星河广场"],"stops":[{"attractionId":37,"name":"幕燕滨江风貌区","category":"自然风光、城市漫游","time":"12:54","endTime":"15:54","transferToNextMinutes":75,"durationMinutes":180,"heatScore":95,"crowdIndex":68,"crowdLevel":"较拥挤","openingHours":"09:00-17:00","crowdAdvice":"客流偏高，建议提前预约并尽量在8:00左右到达","bestVisitTime":"08:00","crowdBasis":"预测模型：景点热度、周边POI距离衰减、日期时段和天气","summary":"南京旅游 RAG 数据集收录。出发前请复核开放、预约和票价信息。","personalTip":"江边风大，带外套，可放风筝或散步。","longitude":118.796219,"latitude":32.128428,"freshness":"今日更新","traffic":{"liveLevel":"未知","roadName":"","description":"未找到可查询的景区周边道路，暂不支持实时路况","sampledAt":"2026-07-16 16:35","averageSpeed":null,"forecastLevel":"未知","forecastReason":"依据近60天同星期及时段的非通勤、非节假日、非异常路况样本","noiseNote":"未发现已识别的通勤或异常噪声","available":true}},{"attractionId":35,"name":"阅江楼","category":"历史人文、自然风光、风景名胜","time":"17:09","endTime":"19:09","transferToNextMinutes":0,"durationMinutes":120,"heatScore":65,"crowdIndex":63,"crowdLevel":"较拥挤","openingHours":"以景区公告为准","crowdAdvice":"客流偏高，建议提前预约并尽量在8:00左右到达","bestVisitTime":"08:00","crowdBasis":"预测模型：景点热度、周边POI距离衰减、日期时段和天气","summary":"南京旅游 RAG 数据集收录。出发前请复核开放、预约和票价信息。","personalTip":"登楼观江景，台阶较多，牵好小孩。","longitude":118.748535,"latitude":32.093857,"freshness":"今日更新","traffic":{"liveLevel":"未知","roadName":"","description":"未找到可查询的景区周边道路，暂不支持实时路况","sampledAt":"2026-07-16 16:35","averageSpeed":null,"forecastLevel":"未知","forecastReason":"依据近60天同星期及时段的非通勤、非节假日、非异常路况样本","noiseNote":"未发现已识别的通勤或异常噪声","available":true}}],"costs":[{"category":"餐饮","label":"早餐","amount":18,"source":"预算估算：高德周边餐饮","pending":false},{"category":"餐饮","label":"午餐","amount":42,"source":"预算估算：高德周边餐饮","pending":false},{"category":"餐饮","label":"晚餐","amount":58,"source":"预算估算：高德周边餐饮","pending":false},{"category":"门票","label":"幕燕滨江风貌区 门票","amount":40,"source":"预算估算：高德 POI 未提供实时票价","pending":false},{"category":"门票","label":"阅江楼 门票","amount":40,"source":"预算估算：高德 POI 未提供实时票价","pending":false},{"category":"交通","label":"当日高德路线交通","amount":17,"source":"预算估算：高德路线距离与交通方式","pending":false},{"category":"预留","label":"弹性消费与价格浮动预留","amount":2410,"source":"预算预留","pending":false}]}],"alternatives":[{"attraction":{"attractionId":11,"name":"中山陵","category":"历史人文、纪念性建筑、风景名胜","time":"待安排","endTime":"待安排","transferToNextMinutes":0,"durationMinutes":180,"heatScore":98,"crowdIndex":50,"crowdLevel":"舒适","openingHours":"中山陵陵寝‘天下为公’陵门以上区域08:30-17:00；墓室关闭不开放。","crowdAdvice":"选择具体日期和时段后重新预测","bestVisitTime":"待计算","crowdBasis":"基础热度与空间分布模型","summary":"南京旅游 RAG 数据集收录。出发前请复核开放、预约和票价信息。","personalTip":"","longitude":118.854097,"latitude":32.054508,"freshness":"今日更新","traffic":null},"recentHeatScore":0,"reason":"综合评分与偏好匹配后的备选景点"},{"attraction":{"attractionId":12,"name":"明孝陵","category":"历史人文、世界遗产、风景名胜","time":"待安排","endTime":"待安排","transferToNextMinutes":0,"durationMinutes":210,"heatScore":98,"crowdIndex":50,"crowdLevel":"舒适","openingHours":"以景区公告为准","crowdAdvice":"选择具体日期和时段后重新预测","bestVisitTime":"待计算","crowdBasis":"基础热度与空间分布模型","summary":"南京旅游 RAG 数据集收录。出发前请复核开放、预约和票价信息。","personalTip":"","longitude":118.840463,"latitude":32.051926,"freshness":"今日更新","traffic":null},"recentHeatScore":0,"reason":"综合评分与偏好匹配后的备选景点"},{"attraction":{"attractionId":16,"name":"总统府","category":"历史人文、博物馆","time":"待安排","endTime":"待安排","transferToNextMinutes":0,"durationMinutes":180,"heatScore":98,"crowdIndex":50,"crowdLevel":"舒适","openingHours":"08:30-18:00","crowdAdvice":"选择具体日期和时段后重新预测","bestVisitTime":"待计算","crowdBasis":"基础热度与空间分布模型","summary":"南京旅游 RAG 数据集收录。出发前请复核开放、预约和票价信息。","personalTip":"","longitude":118.797398,"latitude":32.044228,"freshness":"今日更新","traffic":null},"recentHeatScore":0,"reason":"综合评分与偏好匹配后的备选景点"},{"attraction":{"attractionId":22,"name":"南京博物院","category":"博物馆、历史人文","time":"待安排","endTime":"待安排","transferToNextMinutes":0,"durationMinutes":240,"heatScore":98,"crowdIndex":50,"crowdLevel":"舒适","openingHours":"09:00-20:00","crowdAdvice":"选择具体日期和时段后重新预测","bestVisitTime":"待计算","crowdBasis":"基础热度与空间分布模型","summary":"南京旅游 RAG 数据集收录。出发前请复核开放、预约和票价信息。","personalTip":"","longitude":118.825064,"latitude":32.040802,"freshness":"今日更新","traffic":null},"recentHeatScore":0,"reason":"综合评分与偏好匹配后的备选景点"},{"attraction":{"attractionId":14,"name":"灵谷寺","category":"历史人文、寺庙、风景名胜","time":"待安排","endTime":"待安排","transferToNextMinutes":0,"durationMinutes":150,"heatScore":97,"crowdIndex":50,"crowdLevel":"舒适","openingHours":"08:00-16:30","crowdAdvice":"选择具体日期和时段后重新预测","bestVisitTime":"待计算","crowdBasis":"基础热度与空间分布模型","summary":"南京旅游 RAG 数据集收录。出发前请复核开放、预约和票价信息。","personalTip":"","longitude":118.867693,"latitude":32.055286,"freshness":"今日更新","traffic":null},"recentHeatScore":0,"reason":"综合评分与偏好匹配后的备选景点"}],"budget":{"tier":"经济","target":10500,"min":9450,"max":11550,"estimated":10500,"hasPending":false,"note":"按住宿、餐饮、交通、门票与弹性预留拆分；实时售价需在美团、携程或景区官方页面复核。"}},{"title":"标准","description":"在预算中位数内平衡景点、住宿和餐饮","personalizedAdvice":"带小孩D1钟山景区集中，D2室内博物馆为主，D3纪念馆教育性强，D4较累需调整。","score":94,"days":[{"day":1,"date":"2026-07-16","theme":"玄武区","dailyAdvice":"D1中山陵台阶多，音乐台喂鸽子孩子喜欢，灵谷寺较拥挤可缩短。","weather":{"provider":"WeatherAPI","condition":"Sunny","minTemp":26.9,"maxTemp":34.3,"rainProbability":9,"wind":"23.0 km/h","advice":"天气总体适宜，仍请出发前复核临近预报","forecastTime":"2026-07-16"},"totalMinutes":734,"travelKm":8.5,"accommodation":{"name":"云几·澄心堂度假酒店(南京中山陵店)","address":"孝陵卫街道四方城西路12号","rating":4.7,"longitude":118.844611,"latitude":32.052232,"sameAsPrevious":false,"policy":"13:00后入住 · 次日13:00前退房","luggagePlan":"上午先到酒店寄存行李，游览结束且13:00后办理入住"},"scheduleNotes":["07:00—07:30 起床与洗漱","07:30—07:50 到达云几·澄心堂度假酒店(南京中山陵店)，前台寄存行李（13:00后办理入住）","07:50—07:51 步行从住宿前往早餐门店，约1分钟（高德步行路线）","07:51—08:31 早餐推荐：云几·南京茶馆(钟山店)（高德评分4.6），石象路7号钟山风景名胜区内(南侧)","08:31—08:46 步行前往中山陵，约15分钟（高德步行路线）","天气：Sunny，26.9—34.3℃，降雨概率9%。天气总体适宜，仍请出发前复核临近预报","11:46—12:07 步行前往音乐台，约21分钟（高德步行路线）","12:07—12:09 步行前往午餐门店，约2分钟（高德步行路线）","12:09—13:09 午餐推荐：Degassing·养豆(T80店)（高德评分4.5），小卫街与环紫金山绿道交叉口北240米","13:09—13:11 步行返回音乐台，约2分钟（高德步行路线）","14:11—14:53 公交 202路：小卫街东→灵谷寺公园前往灵谷寺，约42分钟（高德公共交通路线）","17:23—17:53 公交 大环线：灵谷景区→海底世界前往云几·澄心堂度假酒店(南京中山陵店)办理入住，约30分钟（高德公共交通路线）","17:53—18:13 办理入住并将寄存行李送入客房","18:13—18:14 步行前往晚餐门店，约1分钟（高德步行路线）","18:14—19:14 晚餐推荐：云几·南京茶馆(钟山店)（高德评分4.6），石象路7号钟山风景名胜区内(南侧)"],"stops":[{"attractionId":11,"name":"中山陵","category":"历史人文、纪念性建筑、风景名胜","time":"08:46","endTime":"11:46","transferToNextMinutes":21,"durationMinutes":180,"heatScore":98,"crowdIndex":55,"crowdLevel":"舒适","openingHours":"中山陵陵寝‘天下为公’陵门以上区域08:30-17:00；墓室关闭不开放。","crowdAdvice":"预计客流可接受，仍请出发前查看景区官方提示","bestVisitTime":"08:00","crowdBasis":"预测模型：景点热度、周边POI距离衰减、日期时段和天气","summary":"南京旅游 RAG 数据集收录。出发前请复核开放、预约和票价信息。","personalTip":"台阶多，可推婴儿车走坡道，注意防暑。","longitude":118.854097,"latitude":32.054508,"freshness":"今日更新","traffic":{"liveLevel":"未知","roadName":"","description":"未找到可查询的景区周边道路，暂不支持实时路况","sampledAt":"2026-07-16 16:35","averageSpeed":null,"forecastLevel":"未知","forecastReason":"依据近60天同星期及时段的非通勤、非节假日、非异常路况样本","noiseNote":"未发现已识别的通勤或异常噪声","available":true}},{"attractionId":38,"name":"音乐台","category":"历史人文、建筑","time":"13:11","endTime":"14:11","transferToNextMinutes":42,"durationMinutes":60,"heatScore":97,"crowdIndex":70,"crowdLevel":"较拥挤","openingHours":"","crowdAdvice":"客流偏高，建议提前预约并尽量在8:00左右到达","bestVisitTime":"08:00","crowdBasis":"预测模型：景点热度、周边POI距离衰减、日期时段和天气","summary":"南京旅游 RAG 数据集收录。高德关键词会优先返回检票处；本记录采用经人工核验的主体POI坐标。","personalTip":"喂鸽子需零钱，孩子会很喜欢，注意卫生。","longitude":118.850559,"latitude":32.044289,"freshness":"今日更新","traffic":{"liveLevel":"未知","roadName":"","description":"未找到可查询的景区周边道路，暂不支持实时路况","sampledAt":"2026-07-16 16:35","averageSpeed":null,"forecastLevel":"未知","forecastReason":"依据近60天同星期及时段的非通勤、非节假日、非异常路况样本","noiseNote":"未发现已识别的通勤或异常噪声","available":true}},{"attractionId":14,"name":"灵谷寺","category":"历史人文、寺庙、风景名胜","time":"14:53","endTime":"17:23","transferToNextMinutes":0,"durationMinutes":150,"heatScore":97,"crowdIndex":84,"crowdLevel":"拥挤","openingHours":"08:00-16:30","crowdAdvice":"当前时段预计拥挤，建议改到8:00左右或选择备选景点","bestVisitTime":"08:00","crowdBasis":"预测模型：景点热度、周边POI距离衰减、日期时段和天气","summary":"南京旅游 RAG 数据集收录。出发前请复核开放、预约和票价信息。","personalTip":"灵谷寺深松居素面不错，但拥挤，建议早去。","longitude":118.867693,"latitude":32.055286,"freshness":"今日更新","traffic":{"liveLevel":"未知","roadName":"","description":"未找到可查询的景区周边道路，暂不支持实时路况","sampledAt":"2026-07-16 16:35","averageSpeed":null,"forecastLevel":"未知","forecastReason":"依据近60天同星期及时段的非通勤、非节假日、非异常路况样本","noiseNote":"未发现已识别的通勤或异常噪声","available":true}}],"costs":[{"category":"住宿","label":"当晚住宿","amount":350,"source":"预算估算：高德住宿 POI 与档位基准","pending":false},{"category":"餐饮","label":"早餐","amount":30,"source":"预算估算：高德周边餐饮","pending":false},{"category":"餐饮","label":"午餐","amount":65,"source":"预算估算：高德周边餐饮","pending":false},{"category":"餐饮","label":"晚餐","amount":90,"source":"预算估算：高德周边餐饮","pending":false},{"category":"门票","label":"中山陵 门票","amount":120,"source":"预算估算：高德 POI 未提供实时票价","pending":false},{"category":"门票","label":"音乐台 门票","amount":50,"source":"预算估算：高德 POI 未提供实时票价","pending":false},{"category":"门票","label":"灵谷寺 门票","amount":70,"source":"预算估算：高德 POI 未提供实时票价","pending":false},{"category":"交通","label":"当日高德路线交通","amount":4,"source":"预算估算：高德路线距离与交通方式","pending":false},{"category":"预留","label":"弹性消费与价格浮动预留","amount":2971,"source":"预算预留","pending":false}]},{"day":2,"date":"2026-07-17","theme":"秦淮区 · 鼓楼区","dailyAdvice":"D2降雨概率高，大报恩寺和科举博物馆室内为主，先锋书店适合休憩。","weather":{"provider":"WeatherAPI","condition":"Sunny","minTemp":27.2,"maxTemp":33.8,"rainProbability":70,"wind":"23.0 km/h","advice":"降雨概率较高，建议准备雨具并优先室内行程","forecastTime":"2026-07-17"},"totalMinutes":793,"travelKm":25.5,"accommodation":{"name":"云几·澄心堂度假酒店(南京中山陵店)","address":"孝陵卫街道四方城西路12号","rating":4.7,"longitude":118.844611,"latitude":32.052232,"sameAsPrevious":true,"policy":"13:00后入住 · 次日13:00前退房","luggagePlan":"继续住同一酒店，行李留在客房，无需随身游览"},"scheduleNotes":["07:00—07:30 起床与洗漱","07:30—07:31 步行从住宿前往早餐门店，约1分钟（高德步行路线）","07:31—08:11 早餐推荐：云几·南京茶馆(钟山店)（高德评分4.6），石象路7号钟山风景名胜区内(南侧)","08:11—09:30 地铁 地铁2号线：中山陵·下马坊→新街口；地铁1号线：新街口→中华门前往大报恩寺遗址景区，约79分钟（高德公共交通路线）","天气：Sunny，27.2—33.8℃，降雨概率70%。降雨概率较高，建议准备雨具并优先室内行程","12:30—13:04 公交 202路：大报恩寺遗址公园→建康路·夫子庙前往中国科举博物馆，约34分钟（高德公共交通路线）","13:04—13:06 步行前往午餐门店，约2分钟（高德步行路线）","13:06—14:06 午餐推荐：金中鸭血粉丝汤(夫子庙店)（高德评分4.5），大石坝街与夫子庙景区步行街交叉口东北20米","14:06—14:08 步行返回中国科举博物馆，约2分钟（高德步行路线）","16:38—17:02 地铁 地铁5号线：夫子庙→五台山前往先锋书店（五台山店），约24分钟（高德公共交通路线）","18:02—18:09 步行前往晚餐门店，约7分钟（高德步行路线）","18:09—19:09 晚餐推荐：月影韩国餐厅(上海路小区店)（高德评分4.6），上海路87-4号(五台山地铁站3A口步行400米)","19:09—20:13 地铁 地铁5号线：五台山→上海路；地铁2号线：上海路→苜蓿园返回住宿云几·澄心堂度假酒店(南京中山陵店)，约64分钟（高德公共交通路线）"],"stops":[{"attractionId":30,"name":"大报恩寺遗址景区","category":"历史人文、博物馆","time":"09:30","endTime":"12:30","transferToNextMinutes":34,"durationMinutes":180,"heatScore":97,"crowdIndex":48,"crowdLevel":"舒适","openingHours":"以景区公告为准","crowdAdvice":"预计客流可接受，仍请出发前查看景区官方提示","bestVisitTime":"08:00","crowdBasis":"预测模型：景点热度、周边POI距离衰减、日期时段和天气","summary":"南京旅游 RAG 数据集收录。出发前请复核开放、预约和票价信息。","personalTip":"遗址景区有互动体验，孩子可参与，提前预约。","longitude":118.78301,"latitude":32.009204,"freshness":"今日更新","traffic":{"liveLevel":"未知","roadName":"","description":"未找到可查询的景区周边道路，暂不支持实时路况","sampledAt":"2026-07-16 16:35","averageSpeed":null,"forecastLevel":"未知","forecastReason":"依据近60天同星期及时段的非通勤、非节假日、非异常路况样本","noiseNote":"未发现已识别的通勤或异常噪声","available":true}},{"attractionId":40,"name":"中国科举博物馆","category":"博物馆、历史人文","time":"14:08","endTime":"16:38","transferToNextMinutes":24,"durationMinutes":150,"heatScore":97,"crowdIndex":63,"crowdLevel":"较拥挤","openingHours":"","crowdAdvice":"客流偏高，建议提前预约并尽量在8:00左右到达","bestVisitTime":"08:00","crowdBasis":"预测模型：景点热度、周边POI距离衰减、日期时段和天气","summary":"南京旅游 RAG 数据集收录。高德关键词会返回牌坊或停车点；本记录采用博物馆主体坐标。","personalTip":"科举博物馆有趣味展览，适合学龄儿童。","longitude":118.793256,"latitude":32.020107,"freshness":"今日更新","traffic":{"liveLevel":"未知","roadName":"","description":"未找到可查询的景区周边道路，暂不支持实时路况","sampledAt":"2026-07-16 16:35","averageSpeed":null,"forecastLevel":"未知","forecastReason":"依据近60天同星期及时段的非通勤、非节假日、非异常路况样本","noiseNote":"未发现已识别的通勤或异常噪声","available":true}},{"attractionId":27,"name":"先锋书店（五台山店）","category":"城市漫游、文化空间","time":"17:02","endTime":"18:02","transferToNextMinutes":0,"durationMinutes":60,"heatScore":98,"crowdIndex":47,"crowdLevel":"舒适","openingHours":"10:00-21:00","crowdAdvice":"预计客流可接受，仍请出发前查看景区官方提示","bestVisitTime":"08:00","crowdBasis":"预测模型：景点热度、周边POI距离衰减、日期时段和天气","summary":"南京旅游 RAG 数据集收录。出发前请复核开放、预约和票价信息。","personalTip":"书店有文创和咖啡，可稍作休息。","longitude":118.773496,"latitude":32.05072,"freshness":"今日更新","traffic":{"liveLevel":"未知","roadName":"","description":"未找到可查询的景区周边道路，暂不支持实时路况","sampledAt":"2026-07-16 16:35","averageSpeed":null,"forecastLevel":"未知","forecastReason":"依据近60天同星期及时段的非通勤、非节假日、非异常路况样本","noiseNote":"未发现已识别的通勤或异常噪声","available":true}}],"costs":[{"category":"住宿","label":"当晚住宿","amount":350,"source":"预算估算：高德住宿 POI 与档位基准","pending":false},{"category":"餐饮","label":"早餐","amount":30,"source":"预算估算：高德周边餐饮","pending":false},{"category":"餐饮","label":"午餐","amount":65,"source":"预算估算：高德周边餐饮","pending":false},{"category":"餐饮","label":"晚餐","amount":90,"source":"预算估算：高德周边餐饮","pending":false},{"category":"门票","label":"大报恩寺遗址景区 门票","amount":70,"source":"预算估算：高德 POI 未提供实时票价","pending":false},{"category":"门票","label":"中国科举博物馆 门票","amount":70,"source":"预算估算：高德 POI 未提供实时票价","pending":false},{"category":"门票","label":"先锋书店（五台山店） 门票","amount":120,"source":"预算估算：高德 POI 未提供实时票价","pending":false},{"category":"交通","label":"当日高德路线交通","amount":12,"source":"预算估算：高德路线距离与交通方式","pending":false},{"category":"预留","label":"弹性消费与价格浮动预留","amount":2943,"source":"预算预留","pending":false}]},{"day":3,"date":"2026-07-18","theme":"建邺区 · 秦淮区","dailyAdvice":"D3纪念馆庄重，朝天宫和甘熙故居有历史感，注意孩子情绪。","weather":{"provider":"WeatherAPI","condition":"Patchy rain nearby","minTemp":24.7,"maxTemp":27.5,"rainProbability":86,"wind":"16.2 km/h","advice":"降雨概率较高，建议准备雨具并优先室内行程","forecastTime":"2026-07-18"},"totalMinutes":783,"travelKm":26.5,"accommodation":{"name":"云几·澄心堂度假酒店(南京中山陵店)","address":"孝陵卫街道四方城西路12号","rating":4.7,"longitude":118.844611,"latitude":32.052232,"sameAsPrevious":true,"policy":"13:00后入住 · 次日13:00前退房","luggagePlan":"继续住同一酒店，行李留在客房，无需随身游览"},"scheduleNotes":["07:00—07:30 起床与洗漱","07:30—07:31 步行从住宿前往早餐门店，约1分钟（高德步行路线）","07:31—08:11 早餐推荐：云几·南京茶馆(钟山店)（高德评分4.6），石象路7号钟山风景名胜区内(南侧)","08:11—09:15 地铁 地铁2号线：中山陵·下马坊→云锦路前往侵华日军南京大屠杀遇难同胞纪念馆，约64分钟（高德公共交通路线）","天气：Patchy rain nearby，24.7—27.5℃，降雨概率86%。降雨概率较高，建议准备雨具并优先室内行程","12:15—12:52 地铁 地铁2号线：云锦路→上海路前往朝天宫，约37分钟（高德公共交通路线）","12:52—13:00 步行前往午餐门店，约8分钟（高德步行路线）","13:00—14:00 午餐推荐：安乐园菜馆(王府大街店)（高德评分4.7），王府大街138号","14:00—14:08 步行返回朝天宫，约8分钟（高德步行路线）","16:08—16:31 步行前往甘熙故居，约23分钟（高德步行路线）","18:01—18:04 步行前往晚餐门店，约3分钟（高德步行路线）","18:04—19:04 晚餐推荐：瓶子菜馆(熙南里店)（高德评分4.7），熙南里10号1617铺位","19:04—20:03 地铁 地铁1号线：三山街→新街口；地铁2号线：新街口→苜蓿园返回住宿云几·澄心堂度假酒店(南京中山陵店)，约59分钟（高德公共交通路线）"],"stops":[{"attractionId":28,"name":"侵华日军南京大屠杀遇难同胞纪念馆","category":"纪念馆、历史人文","time":"09:15","endTime":"12:15","transferToNextMinutes":37,"durationMinutes":180,"heatScore":97,"crowdIndex":52,"crowdLevel":"舒适","openingHours":"以景区公告为准","crowdAdvice":"预计客流可接受，仍请出发前查看景区官方提示","bestVisitTime":"08:00","crowdBasis":"预测模型：景点热度、周边POI距离衰减、日期时段和天气","summary":"南京旅游 RAG 数据集收录。出发前请复核开放、预约和票价信息。","personalTip":"纪念馆内容沉重，建议提前给孩子简单讲解，保持肃穆。","longitude":118.742372,"latitude":32.035217,"freshness":"今日更新","traffic":{"liveLevel":"未知","roadName":"","description":"未找到可查询的景区周边道路，暂不支持实时路况","sampledAt":"2026-07-16 16:35","averageSpeed":null,"forecastLevel":"未知","forecastReason":"依据近60天同星期及时段的非通勤、非节假日、非异常路况样本","noiseNote":"未发现已识别的通勤或异常噪声","available":true}},{"attractionId":21,"name":"朝天宫","category":"历史人文、博物馆","time":"14:08","endTime":"16:08","transferToNextMinutes":23,"durationMinutes":120,"heatScore":97,"crowdIndex":73,"crowdLevel":"较拥挤","openingHours":"09:00-18:00","crowdAdvice":"客流偏高，建议提前预约并尽量在8:00左右到达","bestVisitTime":"08:00","crowdBasis":"预测模型：景点热度、周边POI距离衰减、日期时段和天气","summary":"南京旅游 RAG 数据集收录。出发前请复核开放、预约和票价信息。","personalTip":"朝天宫有古代礼仪展示，孩子可体验。","longitude":118.77532,"latitude":32.034344,"freshness":"今日更新","traffic":{"liveLevel":"未知","roadName":"","description":"未找到可查询的景区周边道路，暂不支持实时路况","sampledAt":"2026-07-16 16:35","averageSpeed":null,"forecastLevel":"未知","forecastReason":"依据近60天同星期及时段的非通勤、非节假日、非异常路况样本","noiseNote":"未发现已识别的通勤或异常噪声","available":true}},{"attractionId":34,"name":"甘熙故居","category":"历史人文、博物馆","time":"16:31","endTime":"18:01","transferToNextMinutes":0,"durationMinutes":90,"heatScore":96,"crowdIndex":75,"crowdLevel":"较拥挤","openingHours":"以景区公告为准","crowdAdvice":"客流偏高，建议提前预约并尽量在8:00左右到达","bestVisitTime":"08:00","crowdBasis":"预测模型：景点热度、周边POI距离衰减、日期时段和天气","summary":"南京旅游 RAG 数据集收录。出发前请复核开放、预约和票价信息。","personalTip":"甘熙故居民俗展有趣，但较拥挤。","longitude":118.7817,"latitude":32.025849,"freshness":"今日更新","traffic":{"liveLevel":"未知","roadName":"","description":"未找到可查询的景区周边道路，暂不支持实时路况","sampledAt":"2026-07-16 16:35","averageSpeed":null,"forecastLevel":"未知","forecastReason":"依据近60天同星期及时段的非通勤、非节假日、非异常路况样本","noiseNote":"未发现已识别的通勤或异常噪声","available":true}}],"costs":[{"category":"住宿","label":"当晚住宿","amount":350,"source":"预算估算：高德住宿 POI 与档位基准","pending":false},{"category":"餐饮","label":"早餐","amount":30,"source":"预算估算：高德周边餐饮","pending":false},{"category":"餐饮","label":"午餐","amount":65,"source":"预算估算：高德周边餐饮","pending":false},{"category":"餐饮","label":"晚餐","amount":90,"source":"预算估算：高德周边餐饮","pending":false},{"category":"门票","label":"侵华日军南京大屠杀遇难同胞纪念馆 门票","amount":50,"source":"预算估算：高德 POI 未提供实时票价","pending":false},{"category":"门票","label":"朝天宫 门票","amount":70,"source":"预算估算：高德 POI 未提供实时票价","pending":false},{"category":"门票","label":"甘熙故居 门票","amount":70,"source":"预算估算：高德 POI 未提供实时票价","pending":false},{"category":"交通","label":"当日高德路线交通","amount":12,"source":"预算估算：高德路线距离与交通方式","pending":false},{"category":"预留","label":"弹性消费与价格浮动预留","amount":3013,"source":"预算预留","pending":false}]},{"day":4,"date":"2026-07-19","theme":"浦口区 · 栖霞区","dailyAdvice":"D4行程紧凑且拥挤，建议删减一个景点，优先幕燕滨江。","weather":null,"totalMinutes":929,"travelKm":44.4,"accommodation":{"name":"悦见公寓(五塘广场地铁站店)","address":"幕府山街道幕府西路29号金域中央广场","rating":5.0,"longitude":118.773075,"latitude":32.106575,"sameAsPrevious":false,"policy":"13:00后入住 · 次日13:00前退房","luggagePlan":"13:00前从上一酒店退房，仅在酒店转场时携带行李；到新酒店后立即寄存，13:00后入住"},"scheduleNotes":["07:00—07:30 起床与洗漱","07:30—07:31 步行从住宿前往早餐门店，约1分钟（高德步行路线）","07:31—08:11 早餐推荐：云几·南京茶馆(钟山店)（高德评分4.6），石象路7号钟山风景名胜区内(南侧)","08:11—08:12 步行返回原住宿办理退房，约1分钟（高德步行路线）","08:12—08:27 在云几·澄心堂度假酒店(南京中山陵店)办理退房（酒店要求13:00前）","08:27—09:18 打车携带行李前往新住宿悦见公寓(五塘广场地铁站店)，约51分钟（高德驾车路线）","09:18—09:33 在新住宿前台寄存行李，13:00后办理入住","09:33—10:45 地铁 地铁3号线：五塘广场→泰冯路；地铁S8号线(宁天线)：泰冯路→长江大桥北从新住宿前往南京长江大桥，约72分钟（高德公共交通路线）","12:15—14:04 公交 535路：江山路·大桥北路→许府巷；35路：中央门南→幕府创新小镇；30路：中央门南→幕府创新小镇前往幕燕滨江风貌区，约109分钟（高德公共交通路线）","17:04—17:30 打车前往阅江楼，约26分钟（高德驾车路线）","19:30—20:30 午餐推荐：德克士(101明潮里店)（高德评分4.4），建宁路196号101明潮里","20:30—21:08 地铁 地铁5号线：盐仓桥→福建路；地铁7号线：福建路→幕府西路前往悦见公寓(五塘广场地铁站店)办理入住，约38分钟（高德公共交通路线）","21:08—21:28 办理入住并将寄存行李送入客房","21:28—21:29 步行前往晚餐门店，约1分钟（高德步行路线）","21:29—22:29 晚餐推荐：刘记酱骨头东北家常菜馆（高德评分4.5），幕府西路金域广场29-8"],"stops":[{"attractionId":36,"name":"南京长江大桥","category":"城市地标、历史人文","time":"10:45","endTime":"12:15","transferToNextMinutes":109,"durationMinutes":90,"heatScore":97,"crowdIndex":93,"crowdLevel":"拥挤","openingHours":"24小时营业","crowdAdvice":"当前时段预计拥挤，建议改到8:00左右或选择备选景点","bestVisitTime":"08:00","crowdBasis":"预测模型：景点热度、周边POI距离衰减、日期时段和天气","summary":"南京旅游 RAG 数据集收录。出发前请复核开放、预约和票价信息。","personalTip":"大桥可远观，不必登桥，注意安全。","longitude":118.738835,"latitude":32.116067,"freshness":"今日更新","traffic":{"liveLevel":"未知","roadName":"","description":"未找到可查询的景区周边道路，暂不支持实时路况","sampledAt":"2026-07-16 16:35","averageSpeed":null,"forecastLevel":"未知","forecastReason":"依据近60天同星期及时段的非通勤、非节假日、非异常路况样本","noiseNote":"未发现已识别的通勤或异常噪声","available":true}},{"attractionId":37,"name":"幕燕滨江风貌区","category":"自然风光、城市漫游","time":"14:04","endTime":"17:04","transferToNextMinutes":26,"durationMinutes":180,"heatScore":95,"crowdIndex":87,"crowdLevel":"拥挤","openingHours":"09:00-17:00","crowdAdvice":"当前时段预计拥挤，建议改到8:00左右或选择备选景点","bestVisitTime":"08:00","crowdBasis":"预测模型：景点热度、周边POI距离衰减、日期时段和天气","summary":"南京旅游 RAG 数据集收录。出发前请复核开放、预约和票价信息。","personalTip":"滨江风貌区适合散步，孩子可玩沙，但注意闭园时间。","longitude":118.796219,"latitude":32.128428,"freshness":"今日更新","traffic":{"liveLevel":"未知","roadName":"","description":"未找到可查询的景区周边道路，暂不支持实时路况","sampledAt":"2026-07-16 16:35","averageSpeed":null,"forecastLevel":"未知","forecastReason":"依据近60天同星期及时段的非通勤、非节假日、非异常路况样本","noiseNote":"未发现已识别的通勤或异常噪声","available":true}},{"attractionId":35,"name":"阅江楼","category":"历史人文、自然风光、风景名胜","time":"17:30","endTime":"19:30","transferToNextMinutes":0,"durationMinutes":120,"heatScore":65,"crowdIndex":63,"crowdLevel":"较拥挤","openingHours":"以景区公告为准","crowdAdvice":"客流偏高，建议提前预约并尽量在8:00左右到达","bestVisitTime":"08:00","crowdBasis":"预测模型：景点热度、周边POI距离衰减、日期时段和天气","summary":"南京旅游 RAG 数据集收录。出发前请复核开放、预约和票价信息。","personalTip":"阅江楼登高望远，但时间紧张，可略过。","longitude":118.748535,"latitude":32.093857,"freshness":"今日更新","traffic":{"liveLevel":"未知","roadName":"","description":"未找到可查询的景区周边道路，暂不支持实时路况","sampledAt":"2026-07-16 16:35","averageSpeed":null,"forecastLevel":"未知","forecastReason":"依据近60天同星期及时段的非通勤、非节假日、非异常路况样本","noiseNote":"未发现已识别的通勤或异常噪声","available":true}}],"costs":[{"category":"餐饮","label":"早餐","amount":30,"source":"预算估算：高德周边餐饮","pending":false},{"category":"餐饮","label":"午餐","amount":65,"source":"预算估算：高德周边餐饮","pending":false},{"category":"餐饮","label":"晚餐","amount":90,"source":"预算估算：高德周边餐饮","pending":false},{"category":"门票","label":"南京长江大桥 门票","amount":50,"source":"预算估算：高德 POI 未提供实时票价","pending":false},{"category":"门票","label":"幕燕滨江风貌区 门票","amount":50,"source":"预算估算：高德 POI 未提供实时票价","pending":false},{"category":"门票","label":"阅江楼 门票","amount":50,"source":"预算估算：高德 POI 未提供实时票价","pending":false},{"category":"交通","label":"当日高德路线交通","amount":20,"source":"预算估算：高德路线距离与交通方式","pending":false},{"category":"预留","label":"弹性消费与价格浮动预留","amount":3395,"source":"预算预留","pending":false}]}],"alternatives":[{"attraction":{"attractionId":12,"name":"明孝陵","category":"历史人文、世界遗产、风景名胜","time":"待安排","endTime":"待安排","transferToNextMinutes":0,"durationMinutes":210,"heatScore":98,"crowdIndex":50,"crowdLevel":"舒适","openingHours":"以景区公告为准","crowdAdvice":"选择具体日期和时段后重新预测","bestVisitTime":"待计算","crowdBasis":"基础热度与空间分布模型","summary":"南京旅游 RAG 数据集收录。出发前请复核开放、预约和票价信息。","personalTip":"","longitude":118.840463,"latitude":32.051926,"freshness":"今日更新","traffic":null},"recentHeatScore":0,"reason":"综合评分与偏好匹配后的备选景点"},{"attraction":{"attractionId":15,"name":"玄武湖公园","category":"自然风光、城市公园","time":"待安排","endTime":"待安排","transferToNextMinutes":0,"durationMinutes":180,"heatScore":98,"crowdIndex":50,"crowdLevel":"舒适","openingHours":"24小时营业","crowdAdvice":"选择具体日期和时段后重新预测","bestVisitTime":"待计算","crowdBasis":"基础热度与空间分布模型","summary":"南京旅游 RAG 数据集收录。出发前请复核开放、预约和票价信息。","personalTip":"","longitude":118.812688,"latitude":32.069455,"freshness":"今日更新","traffic":null},"recentHeatScore":0,"reason":"综合评分与偏好匹配后的备选景点"},{"attraction":{"attractionId":16,"name":"总统府","category":"历史人文、博物馆","time":"待安排","endTime":"待安排","transferToNextMinutes":0,"durationMinutes":180,"heatScore":98,"crowdIndex":50,"crowdLevel":"舒适","openingHours":"08:30-18:00","crowdAdvice":"选择具体日期和时段后重新预测","bestVisitTime":"待计算","crowdBasis":"基础热度与空间分布模型","summary":"南京旅游 RAG 数据集收录。出发前请复核开放、预约和票价信息。","personalTip":"","longitude":118.797398,"latitude":32.044228,"freshness":"今日更新","traffic":null},"recentHeatScore":0,"reason":"综合评分与偏好匹配后的备选景点"},{"attraction":{"attractionId":19,"name":"牛首山文化旅游区","category":"历史人文、自然风光、风景名胜","time":"待安排","endTime":"待安排","transferToNextMinutes":0,"durationMinutes":300,"heatScore":98,"crowdIndex":50,"crowdLevel":"舒适","openingHours":"以景区公告为准","crowdAdvice":"选择具体日期和时段后重新预测","bestVisitTime":"待计算","crowdBasis":"基础热度与空间分布模型","summary":"南京旅游 RAG 数据集收录。出发前请复核开放、预约和票价信息。","personalTip":"","longitude":118.74415,"latitude":31.903309,"freshness":"今日更新","traffic":null},"recentHeatScore":0,"reason":"综合评分与偏好匹配后的备选景点"},{"attraction":{"attractionId":22,"name":"南京博物院","category":"博物馆、历史人文","time":"待安排","endTime":"待安排","transferToNextMinutes":0,"durationMinutes":240,"heatScore":98,"crowdIndex":50,"crowdLevel":"舒适","openingHours":"09:00-20:00","crowdAdvice":"选择具体日期和时段后重新预测","bestVisitTime":"待计算","crowdBasis":"基础热度与空间分布模型","summary":"南京旅游 RAG 数据集收录。出发前请复核开放、预约和票价信息。","personalTip":"","longitude":118.825064,"latitude":32.040802,"freshness":"今日更新","traffic":null},"recentHeatScore":0,"reason":"综合评分与偏好匹配后的备选景点"}],"budget":{"tier":"标准","target":15000,"min":13500,"max":16500,"estimated":15000,"hasPending":false,"note":"按住宿、餐饮、交通、门票与弹性预留拆分；实时售价需在美团、携程或景区官方页面复核。"}},{"title":"舒适","description":"在预算上限内提升住宿、餐饮和转场舒适度","personalizedAdvice":"带小孩推荐此方案，D1明孝陵+博物院，D2老门东+总统府，D3夫子庙夜游，D4较累建议调整。","score":92,"days":[{"day":1,"date":"2026-07-16","theme":"玄武区","dailyAdvice":"D1明孝陵神道适合散步，博物院内容丰富，注意闭馆时间。","weather":{"provider":"WeatherAPI","condition":"Sunny","minTemp":26.9,"maxTemp":34.3,"rainProbability":9,"wind":"23.0 km/h","advice":"天气总体适宜，仍请出发前复核临近预报","forecastTime":"2026-07-16"},"totalMinutes":941,"travelKm":9.1,"accommodation":{"name":"艺间·隐世酒店(南京博物院店)","address":"梅园新村街道前半山园12号1幢1层","rating":4.8,"longitude":118.826058,"latitude":32.039846,"sameAsPrevious":false,"policy":"13:00后入住 · 次日13:00前退房","luggagePlan":"上午先到酒店寄存行李，游览结束且13:00后办理入住"},"scheduleNotes":["07:00—07:30 起床与洗漱","07:30—07:50 到达艺间·隐世酒店(南京博物院店)，前台寄存行李（13:00后办理入住）","07:50—08:30 早餐推荐：住宿附近独立早餐店（请结合实时营业状态选择）","08:30—09:04 公交 20路观光区间：卫桥→明孝陵从住宿前往明孝陵，约34分钟（高德公共交通路线）","天气：Sunny，26.9—34.3℃，降雨概率9%。天气总体适宜，仍请出发前复核临近预报","09:04—11:30 景点周边短暂休息","11:30—11:46 步行前往午餐门店，约16分钟（高德步行路线）","11:46—12:46 午餐推荐：云几·紫金山（高德评分4.7），紫金山风景名胜区内石象路7-9号","12:46—13:02 步行返回明孝陵，约16分钟（高德步行路线）","16:32—17:06 公交 G33路：中山植物园→中山门前往南京博物院，约34分钟（高德公共交通路线）","21:06—21:11 步行前往艺间·隐世酒店(南京博物院店)办理入住，约5分钟（高德步行路线）","21:11—21:31 办理入住并将寄存行李送入客房","21:31—21:36 步行前往晚餐门店，约5分钟（高德步行路线）","21:36—22:36 晚餐推荐：金原鸭血粉丝汤(中山东路店)（高德评分4.5），中山东路与李府街交叉口西60米","22:36—22:41 步行返回住宿艺间·隐世酒店(南京博物院店)，约5分钟（高德步行路线）"],"stops":[{"attractionId":12,"name":"明孝陵","category":"历史人文、世界遗产、风景名胜","time":"13:02","endTime":"16:32","transferToNextMinutes":34,"durationMinutes":210,"heatScore":98,"crowdIndex":70,"crowdLevel":"较拥挤","openingHours":"以景区公告为准","crowdAdvice":"客流偏高，建议提前预约并尽量在8:00左右到达","bestVisitTime":"08:00","crowdBasis":"预测模型：景点热度、周边POI距离衰减、日期时段和天气","summary":"南京旅游 RAG 数据集收录。出发前请复核开放、预约和票价信息。","personalTip":"神道石象路孩子喜欢，可推车，注意防蚊。","longitude":118.840463,"latitude":32.051926,"freshness":"今日更新","traffic":{"liveLevel":"未知","roadName":"","description":"未找到可查询的景区周边道路，暂不支持实时路况","sampledAt":"2026-07-16 16:35","averageSpeed":null,"forecastLevel":"未知","forecastReason":"依据近60天同星期及时段的非通勤、非节假日、非异常路况样本","noiseNote":"未发现已识别的通勤或异常噪声","available":true}},{"attractionId":22,"name":"南京博物院","category":"博物馆、历史人文","time":"17:06","endTime":"21:06","transferToNextMinutes":0,"durationMinutes":240,"heatScore":98,"crowdIndex":69,"crowdLevel":"较拥挤","openingHours":"09:00-20:00","crowdAdvice":"客流偏高，建议提前预约并尽量在8:00左右到达","bestVisitTime":"08:00","crowdBasis":"预测模型：景点热度、周边POI距离衰减、日期时段和天气","summary":"南京旅游 RAG 数据集收录。出发前请复核开放、预约和票价信息。","personalTip":"博物院有儿童体验区，提前预约，建议下午入馆。","longitude":118.825064,"latitude":32.040802,"freshness":"今日更新","traffic":{"liveLevel":"未知","roadName":"","description":"未找到可查询的景区周边道路，暂不支持实时路况","sampledAt":"2026-07-16 16:35","averageSpeed":null,"forecastLevel":"未知","forecastReason":"依据近60天同星期及时段的非通勤、非节假日、非异常路况样本","noiseNote":"未发现已识别的通勤或异常噪声","available":true}}],"costs":[{"category":"住宿","label":"当晚住宿","amount":520,"source":"预算估算：高德住宿 POI 与档位基准","pending":false},{"category":"餐饮","label":"早餐","amount":48,"source":"预算估算：高德周边餐饮","pending":false},{"category":"餐饮","label":"午餐","amount":110,"source":"预算估算：高德周边餐饮","pending":false},{"category":"餐饮","label":"晚餐","amount":150,"source":"预算估算：高德周边餐饮","pending":false},{"category":"门票","label":"明孝陵 门票","amount":60,"source":"预算估算：高德 POI 未提供实时票价","pending":false},{"category":"门票","label":"南京博物院 门票","amount":84,"source":"预算估算：高德 POI 未提供实时票价","pending":false},{"category":"交通","label":"当日高德路线交通","amount":5,"source":"预算估算：高德路线距离与交通方式","pending":false},{"category":"预留","label":"弹性消费与价格浮动预留","amount":3898,"source":"预算预留","pending":false}]},{"day":2,"date":"2026-07-17","theme":"秦淮区 · 玄武区","dailyAdvice":"D2中华门城堡可登城，老门东美食多，总统府历史感强。","weather":{"provider":"WeatherAPI","condition":"Sunny","minTemp":27.2,"maxTemp":33.8,"rainProbability":70,"wind":"23.0 km/h","advice":"降雨概率较高，建议准备雨具并优先室内行程","forecastTime":"2026-07-17"},"totalMinutes":787,"travelKm":16.5,"accommodation":{"name":"艺间·隐世酒店(南京博物院店)","address":"梅园新村街道前半山园12号1幢1层","rating":4.8,"longitude":118.826058,"latitude":32.039846,"sameAsPrevious":true,"policy":"13:00后入住 · 次日13:00前退房","luggagePlan":"继续住同一酒店，行李留在客房，无需随身游览"},"scheduleNotes":["07:00—07:30 起床与洗漱","07:30—08:10 早餐推荐：住宿附近独立早餐店（请结合实时营业状态选择）","08:10—09:00 地铁 地铁2号线：明故宫→新街口；地铁1号线：新街口→中华门从住宿前往中华门城堡，约50分钟（高德公共交通路线）","天气：Sunny，27.2—33.8℃，降雨概率70%。降雨概率较高，建议准备雨具并优先室内行程","11:00—11:04 步行前往老门东历史文化街区，约4分钟（高德步行路线）","11:04—11:30 景点周边短暂休息","11:30—11:33 步行前往午餐门店，约3分钟（高德步行路线）","11:33—12:33 午餐推荐：无名老卤面(中华门总店)（高德评分4.7），中华路533号","12:33—12:36 步行返回老门东历史文化街区，约3分钟（高德步行路线）","15:06—15:39 公交 2路：中华门城堡→大行宫北前往总统府，约33分钟（高德公共交通路线）","18:39—18:44 步行前往晚餐门店，约5分钟（高德步行路线）","18:44—19:44 晚餐推荐：烤隐·海鲜烧烤精酿啤酒(1912店)（高德评分4.5），太平北路60号1912街区5号楼(近时光车站)","19:44—20:07 地铁 地铁2号线：大行宫→明故宫返回住宿艺间·隐世酒店(南京博物院店)，约23分钟（高德公共交通路线）"],"stops":[{"attractionId":31,"name":"中华门城堡","category":"历史人文、城墙","time":"09:00","endTime":"11:00","transferToNextMinutes":4,"durationMinutes":120,"heatScore":97,"crowdIndex":49,"crowdLevel":"舒适","openingHours":"以景区公告为准","crowdAdvice":"预计客流可接受，仍请出发前查看景区官方提示","bestVisitTime":"08:00","crowdBasis":"预测模型：景点热度、周边POI距离衰减、日期时段和天气","summary":"南京旅游 RAG 数据集收录。出发前请复核开放、预约和票价信息。","personalTip":"城堡台阶多，牵好小孩，可俯瞰老门东。","longitude":118.781821,"latitude":32.0128,"freshness":"今日更新","traffic":{"liveLevel":"未知","roadName":"","description":"未找到可查询的景区周边道路，暂不支持实时路况","sampledAt":"2026-07-16 16:35","averageSpeed":null,"forecastLevel":"未知","forecastReason":"依据近60天同星期及时段的非通勤、非节假日、非异常路况样本","noiseNote":"未发现已识别的通勤或异常噪声","available":true}},{"attractionId":39,"name":"老门东历史文化街区","category":"城市漫游、历史人文、美食街区","time":"12:36","endTime":"15:06","transferToNextMinutes":33,"durationMinutes":150,"heatScore":97,"crowdIndex":49,"crowdLevel":"舒适","openingHours":"","crowdAdvice":"预计客流可接受，仍请出发前查看景区官方提示","bestVisitTime":"08:00","crowdBasis":"预测模型：景点热度、周边POI距离衰减、日期时段和天气","summary":"南京旅游 RAG 数据集收录。高德关键词会优先返回北门寄存点；本记录采用街区主体坐标。","personalTip":"老门东有小吃和文创，孩子会喜欢。","longitude":118.780668,"latitude":32.014823,"freshness":"今日更新","traffic":{"liveLevel":"未知","roadName":"","description":"未找到可查询的景区周边道路，暂不支持实时路况","sampledAt":"2026-07-16 16:35","averageSpeed":null,"forecastLevel":"未知","forecastReason":"依据近60天同星期及时段的非通勤、非节假日、非异常路况样本","noiseNote":"未发现已识别的通勤或异常噪声","available":true}},{"attractionId":16,"name":"总统府","category":"历史人文、博物馆","time":"15:39","endTime":"18:39","transferToNextMinutes":0,"durationMinutes":180,"heatScore":98,"crowdIndex":62,"crowdLevel":"较拥挤","openingHours":"08:30-18:00","crowdAdvice":"客流偏高，建议提前预约并尽量在8:00左右到达","bestVisitTime":"08:00","crowdBasis":"预测模型：景点热度、周边POI距离衰减、日期时段和天气","summary":"南京旅游 RAG 数据集收录。出发前请复核开放、预约和票价信息。","personalTip":"总统府花园可休息，室内展览注意孩子耐心。","longitude":118.797398,"latitude":32.044228,"freshness":"今日更新","traffic":{"liveLevel":"未知","roadName":"","description":"未找到可查询的景区周边道路，暂不支持实时路况","sampledAt":"2026-07-16 16:35","averageSpeed":null,"forecastLevel":"未知","forecastReason":"依据近60天同星期及时段的非通勤、非节假日、非异常路况样本","noiseNote":"未发现已识别的通勤或异常噪声","available":true}}],"costs":[{"category":"住宿","label":"当晚住宿","amount":520,"source":"预算估算：高德住宿 POI 与档位基准","pending":false},{"category":"餐饮","label":"早餐","amount":48,"source":"预算估算：高德周边餐饮","pending":false},{"category":"餐饮","label":"午餐","amount":110,"source":"预算估算：高德周边餐饮","pending":false},{"category":"餐饮","label":"晚餐","amount":150,"source":"预算估算：高德周边餐饮","pending":false},{"category":"门票","label":"中华门城堡 门票","amount":60,"source":"预算估算：高德 POI 未提供实时票价","pending":false},{"category":"门票","label":"老门东历史文化街区 门票","amount":60,"source":"预算估算：高德 POI 未提供实时票价","pending":false},{"category":"门票","label":"总统府 门票","amount":84,"source":"预算估算：高德 POI 未提供实时票价","pending":false},{"category":"交通","label":"当日高德路线交通","amount":8,"source":"预算估算：高德路线距离与交通方式","pending":false},{"category":"预留","label":"弹性消费与价格浮动预留","amount":3835,"source":"预算预留","pending":false}]},{"day":3,"date":"2026-07-18","theme":"鼓楼区 · 秦淮区","dailyAdvice":"D3颐和路适合拍照，瞻园园林精巧，夫子庙夜游人多注意安全。","weather":{"provider":"WeatherAPI","condition":"Partly Cloudy","minTemp":24.5,"maxTemp":27.3,"rainProbability":85,"wind":"16.6 km/h","advice":"降雨概率较高，建议准备雨具并优先室内行程","forecastTime":"2026-07-18"},"totalMinutes":725,"travelKm":21.1,"accommodation":{"name":"艺间·隐世酒店(南京博物院店)","address":"梅园新村街道前半山园12号1幢1层","rating":4.8,"longitude":118.826058,"latitude":32.039846,"sameAsPrevious":true,"policy":"13:00后入住 · 次日13:00前退房","luggagePlan":"继续住同一酒店，行李留在客房，无需随身游览"},"scheduleNotes":["07:00—07:30 起床与洗漱","07:30—08:10 早餐推荐：住宿附近独立早餐店（请结合实时营业状态选择）","08:10—08:57 地铁 地铁2号线：明故宫→上海路；地铁5号线：上海路→青春广场从住宿前往颐和路历史文化街区，约47分钟（高德公共交通路线）","天气：Partly Cloudy，24.5—27.3℃，降雨概率85%。降雨概率较高，建议准备雨具并优先室内行程","10:57—11:33 地铁 地铁5号线：青春广场→三山街前往瞻园，约36分钟（高德公共交通路线）","11:33—11:37 步行前往午餐门店，约4分钟（高德步行路线）","11:37—12:37 午餐推荐：南京大牌档(夫子庙瞻园茂业店)（高德评分4.7），建康路2号南京茂业天地外街1F层01012A","12:37—12:41 步行返回瞻园，约4分钟（高德步行路线）","14:11—14:18 步行前往夫子庙秦淮风光带，约7分钟（高德步行路线）","17:18—17:30 自由休息并前往晚餐门店","17:30—18:30 晚餐推荐：最后景点附近餐厅（请结合实时营业状态选择）","18:30—19:05 地铁 地铁3号线：夫子庙→大行宫；地铁2号线：大行宫→明故宫返回住宿艺间·隐世酒店(南京博物院店)，约35分钟（高德公共交通路线）"],"stops":[{"attractionId":18,"name":"颐和路历史文化街区","category":"城市漫游、历史人文","time":"08:57","endTime":"10:57","transferToNextMinutes":36,"durationMinutes":120,"heatScore":97,"crowdIndex":43,"crowdLevel":"舒适","openingHours":"以景区公告为准","crowdAdvice":"预计客流可接受，仍请出发前查看景区官方提示","bestVisitTime":"08:00","crowdBasis":"预测模型：景点热度、周边POI距离衰减、日期时段和天气","summary":"南京旅游 RAG 数据集收录。出发前请复核开放、预约和票价信息。","personalTip":"颐和路梧桐树荫好，可骑行或散步。","longitude":118.768152,"latitude":32.063949,"freshness":"今日更新","traffic":{"liveLevel":"未知","roadName":"","description":"未找到可查询的景区周边道路，暂不支持实时路况","sampledAt":"2026-07-16 16:35","averageSpeed":null,"forecastLevel":"未知","forecastReason":"依据近60天同星期及时段的非通勤、非节假日、非异常路况样本","noiseNote":"未发现已识别的通勤或异常噪声","available":true}},{"attractionId":32,"name":"瞻园","category":"历史人文、园林","time":"12:41","endTime":"14:11","transferToNextMinutes":7,"durationMinutes":90,"heatScore":97,"crowdIndex":59,"crowdLevel":"舒适","openingHours":"08:30-20:30","crowdAdvice":"预计客流可接受，仍请出发前查看景区官方提示","bestVisitTime":"08:00","crowdBasis":"预测模型：景点热度、周边POI距离衰减、日期时段和天气","summary":"南京旅游 RAG 数据集收录。出发前请复核开放、预约和票价信息。","personalTip":"瞻园假山有趣，但注意孩子安全。","longitude":118.785163,"latitude":32.021034,"freshness":"今日更新","traffic":{"liveLevel":"未知","roadName":"","description":"未找到可查询的景区周边道路，暂不支持实时路况","sampledAt":"2026-07-16 16:35","averageSpeed":null,"forecastLevel":"未知","forecastReason":"依据近60天同星期及时段的非通勤、非节假日、非异常路况样本","noiseNote":"未发现已识别的通勤或异常噪声","available":true}},{"attractionId":20,"name":"夫子庙秦淮风光带","category":"历史人文、城市漫游、夜游","time":"14:18","endTime":"17:18","transferToNextMinutes":0,"durationMinutes":180,"heatScore":98,"crowdIndex":76,"crowdLevel":"较拥挤","openingHours":"24小时营业","crowdAdvice":"客流偏高，建议提前预约并尽量在8:00左右到达","bestVisitTime":"08:00","crowdBasis":"预测模型：景点热度、周边POI距离衰减、日期时段和天气","summary":"南京旅游 RAG 数据集收录。出发前请复核开放、预约和票价信息。","personalTip":"夫子庙晚上热闹，看花灯，牵好小孩防走失。","longitude":118.788972,"latitude":32.020699,"freshness":"今日更新","traffic":{"liveLevel":"未知","roadName":"","description":"未找到可查询的景区周边道路，暂不支持实时路况","sampledAt":"2026-07-16 16:35","averageSpeed":null,"forecastLevel":"未知","forecastReason":"依据近60天同星期及时段的非通勤、非节假日、非异常路况样本","noiseNote":"未发现已识别的通勤或异常噪声","available":true}}],"costs":[{"category":"住宿","label":"当晚住宿","amount":520,"source":"预算估算：高德住宿 POI 与档位基准","pending":false},{"category":"餐饮","label":"早餐","amount":48,"source":"预算估算：高德周边餐饮","pending":false},{"category":"餐饮","label":"午餐","amount":110,"source":"预算估算：高德周边餐饮","pending":false},{"category":"餐饮","label":"晚餐","amount":150,"source":"预算估算：高德周边餐饮","pending":false},{"category":"门票","label":"颐和路历史文化街区 门票","amount":60,"source":"预算估算：高德 POI 未提供实时票价","pending":false},{"category":"门票","label":"瞻园 门票","amount":60,"source":"预算估算：高德 POI 未提供实时票价","pending":false},{"category":"门票","label":"夫子庙秦淮风光带 门票","amount":60,"source":"预算估算：高德 POI 未提供实时票价","pending":false},{"category":"交通","label":"当日高德路线交通","amount":10,"source":"预算估算：高德路线距离与交通方式","pending":false},{"category":"预留","label":"弹性消费与价格浮动预留","amount":3857,"source":"预算预留","pending":false}]},{"day":4,"date":"2026-07-19","theme":"栖霞区 · 鼓楼区","dailyAdvice":"D4行程过满，建议只去幕燕滨江和阅江楼，放弃长江大桥。","weather":null,"totalMinutes":-399,"travelKm":43.5,"accommodation":{"name":"长彦公寓(南京五塘广场地铁站店)","address":"宝塔桥街道幕府西路17号610室","rating":4.8,"longitude":118.774281,"latitude":32.107396,"sameAsPrevious":false,"policy":"13:00后入住 · 次日13:00前退房","luggagePlan":"13:00前从上一酒店退房，仅在酒店转场时携带行李；到新酒店后立即寄存，13:00后入住"},"scheduleNotes":["07:00—07:30 起床与洗漱","07:30—08:10 早餐推荐：住宿附近独立早餐店（请结合实时营业状态选择）","08:10—08:25 在艺间·隐世酒店(南京博物院店)办理退房（酒店要求13:00前）","08:25—09:15 地铁 地铁2号线：明故宫→大行宫；地铁3号线：大行宫→五塘广场携带行李前往新住宿长彦公寓(南京五塘广场地铁站店)，约50分钟（高德公共交通路线）","09:15—09:30 在新住宿前台寄存行李，13:00后办理入住","09:30—09:44 打车从新住宿前往幕燕滨江风貌区，约14分钟（高德驾车路线）","09:44—11:30 景点周边短暂休息","11:30—11:48 打车前往午餐门店，约18分钟（高德驾车路线）","11:48—12:48 午餐推荐：幕府庭院（高德评分4.6），长安路幕府创新小镇A2栋","12:48—13:03 打车返回幕燕滨江风貌区，约15分钟（高德驾车路线）","16:03—17:18 地铁 地铁7号线：幕府山→福建路；地铁5号线：福建路→盐仓桥前往阅江楼，约75分钟（高德公共交通路线）","19:18—20:17 公交 550路：兴中门→大桥北路隧道南前往南京长江大桥，约59分钟（高德公共交通路线）","21:47—23:00 地铁 地铁S8号线(宁天线)：长江大桥北→泰冯路；地铁3号线：泰冯路→五塘广场前往长彦公寓(南京五塘广场地铁站店)办理入住，约73分钟（高德公共交通路线）","23:00—23:20 办理入住并将寄存行李送入客房","23:20—23:21 步行前往晚餐门店，约1分钟（高德步行路线）","23:21—00:21 晚餐推荐：陈记一牛火锅(星河广场店)（高德评分4.8），幕府西路11-3号(五塘广场地铁站5号口步行370米)"],"stops":[{"attractionId":37,"name":"幕燕滨江风貌区","category":"自然风光、城市漫游","time":"13:03","endTime":"16:03","transferToNextMinutes":75,"durationMinutes":180,"heatScore":95,"crowdIndex":68,"crowdLevel":"较拥挤","openingHours":"09:00-17:00","crowdAdvice":"客流偏高，建议提前预约并尽量在8:00左右到达","bestVisitTime":"08:00","crowdBasis":"预测模型：景点热度、周边POI距离衰减、日期时段和天气","summary":"南京旅游 RAG 数据集收录。出发前请复核开放、预约和票价信息。","personalTip":"滨江公园可野餐，孩子可奔跑，注意防晒。","longitude":118.796219,"latitude":32.128428,"freshness":"今日更新","traffic":{"liveLevel":"未知","roadName":"","description":"未找到可查询的景区周边道路，暂不支持实时路况","sampledAt":"2026-07-16 16:35","averageSpeed":null,"forecastLevel":"未知","forecastReason":"依据近60天同星期及时段的非通勤、非节假日、非异常路况样本","noiseNote":"未发现已识别的通勤或异常噪声","available":true}},{"attractionId":35,"name":"阅江楼","category":"历史人文、自然风光、风景名胜","time":"17:18","endTime":"19:18","transferToNextMinutes":59,"durationMinutes":120,"heatScore":65,"crowdIndex":63,"crowdLevel":"较拥挤","openingHours":"以景区公告为准","crowdAdvice":"客流偏高，建议提前预约并尽量在8:00左右到达","bestVisitTime":"08:00","crowdBasis":"预测模型：景点热度、周边POI距离衰减、日期时段和天气","summary":"南京旅游 RAG 数据集收录。出发前请复核开放、预约和票价信息。","personalTip":"阅江楼登楼观江，台阶多，可乘电梯。","longitude":118.748535,"latitude":32.093857,"freshness":"今日更新","traffic":{"liveLevel":"未知","roadName":"","description":"未找到可查询的景区周边道路，暂不支持实时路况","sampledAt":"2026-07-16 16:35","averageSpeed":null,"forecastLevel":"未知","forecastReason":"依据近60天同星期及时段的非通勤、非节假日、非异常路况样本","noiseNote":"未发现已识别的通勤或异常噪声","available":true}},{"attractionId":36,"name":"南京长江大桥","category":"城市地标、历史人文","time":"20:17","endTime":"21:47","transferToNextMinutes":0,"durationMinutes":90,"heatScore":97,"crowdIndex":69,"crowdLevel":"较拥挤","openingHours":"24小时营业","crowdAdvice":"客流偏高，建议提前预约并尽量在8:00左右到达","bestVisitTime":"08:00","crowdBasis":"预测模型：景点热度、周边POI距离衰减、日期时段和天气","summary":"南京旅游 RAG 数据集收录。出发前请复核开放、预约和票价信息。","personalTip":"大桥可远观，不必专门前往，节省体力。","longitude":118.738835,"latitude":32.116067,"freshness":"今日更新","traffic":{"liveLevel":"未知","roadName":"","description":"未找到可查询的景区周边道路，暂不支持实时路况","sampledAt":"2026-07-16 16:35","averageSpeed":null,"forecastLevel":"未知","forecastReason":"依据近60天同星期及时段的非通勤、非节假日、非异常路况样本","noiseNote":"未发现已识别的通勤或异常噪声","available":true}}],"costs":[{"category":"餐饮","label":"早餐","amount":48,"source":"预算估算：高德周边餐饮","pending":false},{"category":"餐饮","label":"午餐","amount":110,"source":"预算估算：高德周边餐饮","pending":false},{"category":"餐饮","label":"晚餐","amount":150,"source":"预算估算：高德周边餐饮","pending":false},{"category":"门票","label":"幕燕滨江风貌区 门票","amount":60,"source":"预算估算：高德 POI 未提供实时票价","pending":false},{"category":"门票","label":"阅江楼 门票","amount":60,"source":"预算估算：高德 POI 未提供实时票价","pending":false},{"category":"门票","label":"南京长江大桥 门票","amount":60,"source":"预算估算：高德 POI 未提供实时票价","pending":false},{"category":"交通","label":"当日高德路线交通","amount":20,"source":"预算估算：高德路线距离与交通方式","pending":false},{"category":"预留","label":"弹性消费与价格浮动预留","amount":4367,"source":"预算预留","pending":false}]}],"alternatives":[{"attraction":{"attractionId":11,"name":"中山陵","category":"历史人文、纪念性建筑、风景名胜","time":"待安排","endTime":"待安排","transferToNextMinutes":0,"durationMinutes":180,"heatScore":98,"crowdIndex":50,"crowdLevel":"舒适","openingHours":"中山陵陵寝‘天下为公’陵门以上区域08:30-17:00；墓室关闭不开放。","crowdAdvice":"选择具体日期和时段后重新预测","bestVisitTime":"待计算","crowdBasis":"基础热度与空间分布模型","summary":"南京旅游 RAG 数据集收录。出发前请复核开放、预约和票价信息。","personalTip":"","longitude":118.854097,"latitude":32.054508,"freshness":"今日更新","traffic":null},"recentHeatScore":0,"reason":"综合评分与偏好匹配后的备选景点"},{"attraction":{"attractionId":15,"name":"玄武湖公园","category":"自然风光、城市公园","time":"待安排","endTime":"待安排","transferToNextMinutes":0,"durationMinutes":180,"heatScore":98,"crowdIndex":50,"crowdLevel":"舒适","openingHours":"24小时营业","crowdAdvice":"选择具体日期和时段后重新预测","bestVisitTime":"待计算","crowdBasis":"基础热度与空间分布模型","summary":"南京旅游 RAG 数据集收录。出发前请复核开放、预约和票价信息。","personalTip":"","longitude":118.812688,"latitude":32.069455,"freshness":"今日更新","traffic":null},"recentHeatScore":0,"reason":"综合评分与偏好匹配后的备选景点"},{"attraction":{"attractionId":19,"name":"牛首山文化旅游区","category":"历史人文、自然风光、风景名胜","time":"待安排","endTime":"待安排","transferToNextMinutes":0,"durationMinutes":300,"heatScore":98,"crowdIndex":50,"crowdLevel":"舒适","openingHours":"以景区公告为准","crowdAdvice":"选择具体日期和时段后重新预测","bestVisitTime":"待计算","crowdBasis":"基础热度与空间分布模型","summary":"南京旅游 RAG 数据集收录。出发前请复核开放、预约和票价信息。","personalTip":"","longitude":118.74415,"latitude":31.903309,"freshness":"今日更新","traffic":null},"recentHeatScore":0,"reason":"综合评分与偏好匹配后的备选景点"},{"attraction":{"attractionId":33,"name":"秦淮河画舫夜游","category":"夜游、体验项目","time":"待安排","endTime":"待安排","transferToNextMinutes":0,"durationMinutes":60,"heatScore":98,"crowdIndex":50,"crowdLevel":"舒适","openingHours":"24小时营业","crowdAdvice":"选择具体日期和时段后重新预测","bestVisitTime":"待计算","crowdBasis":"基础热度与空间分布模型","summary":"南京旅游 RAG 数据集收录。出发前请复核开放、预约和票价信息。","personalTip":"","longitude":118.792026,"latitude":32.021196,"freshness":"今日更新","traffic":null},"recentHeatScore":0,"reason":"综合评分与偏好匹配后的备选景点"},{"attraction":{"attractionId":14,"name":"灵谷寺","category":"历史人文、寺庙、风景名胜","time":"待安排","endTime":"待安排","transferToNextMinutes":0,"durationMinutes":150,"heatScore":97,"crowdIndex":50,"crowdLevel":"舒适","openingHours":"08:00-16:30","crowdAdvice":"选择具体日期和时段后重新预测","bestVisitTime":"待计算","crowdBasis":"基础热度与空间分布模型","summary":"南京旅游 RAG 数据集收录。出发前请复核开放、预约和票价信息。","personalTip":"","longitude":118.867693,"latitude":32.055286,"freshness":"今日更新","traffic":null},"recentHeatScore":0,"reason":"综合评分与偏好匹配后的备选景点"}],"budget":{"tier":"舒适","target":19500,"min":17550,"max":21450,"estimated":19500,"hasPending":false,"note":"按住宿、餐饮、交通、门票与弹性预留拆分；实时售价需在美团、携程或景区官方页面复核。"}}],"generatedAt":"2026-07-16T16:36:57.1068139","dataNotice":"热度与客流为带时间戳的辅助预测；出发前请复核景区官方预约、开放和限流公告。","ai":{"enabled":true,"model":"deepseek-chat","status":"DeepSeek 个性化生成成功"}}